supapi/__init__.py
supapi/brawl.py
supapi/clash.py
supapi/exceptions.py
supapi/royale.py
tests/__init__.py
tests/test.py
supapi-0.1.7.dist-info/LICENSE
supapi-0.1.7.dist-info/METADATA
supapi-0.1.7.dist-info/WHEEL
supapi-0.1.7.dist-info/top_level.txt
supapi-0.1.7.dist-info/RECORD
