Metadata-Version: 2.1
Name: supapi
Version: 0.1.7
Summary: The supapi Python module is a versatile and powerful tool designed to simplify the process of retrieving comprehensive data about players, clans, cards, tournaments, clubs, and brawlers from three popular mobile games: Clash of Clans (CoC), Clash Royale, and Brawl Stars. This module is your all-in-one solution for accessing and analyzing game-related information, making it an invaluable resource for developers, gamers, and data enthusiasts alike.
Home-page: https://www.github.com/new92/supapi
Author: new92
Author-email: new92github@gmail.com
Maintainer: new92
Maintainer-email: new92github@gmail.com
License: MIT
Project-URL: Github Repository, https://github.com/new92/supapi
Keywords: python module COC ClashRoyale BrawlStars DataRetrieval GamingAPI MobileGames Supercell Player Clan Tournament Stats Gaming
Classifier: License :: OSI Approved :: MIT License
Classifier: Programming Language :: Python :: 3
Classifier: Programming Language :: Python :: 3.6
Classifier: Programming Language :: Python :: 3.7
Classifier: Programming Language :: Python :: 3.8
Classifier: Programming Language :: Python :: 3.9
Classifier: Programming Language :: Python :: 3.10
Classifier: Programming Language :: Python :: 3.11
Requires-Python: >=3.6
License-File: LICENSE
Requires-Dist: requests
